[
  {
    "answerId": "ANS_sv_20250901_001_001",
    "businessCard": {
      "group1": {
        "email": "goto.takuya@example.com"
      },
      "group2": {
        "lastName": "後藤",
        "firstName": "拓也"
      },
      "group3": {
        "companyName": "顧客戦略株式会社",
        "department": "顧客戦略部",
        "position": "CRMマネージャー"
      },
      "group4": {
        "postalCode": "100-0006",
        "address1": "東京都千代田区有楽町1-1-2",
        "address2": "東京ミッドタウン日比谷 12F"
      },
      "group5": {
        "mobile": "060-1234-5678",
        "tel1": "03-9999-0000",
        "fax": "03-9999-0001"
      },
      "group6": {
        "url": "https://customer-strategy.example.com"
      }
    }
  },
  {
    "answerId": "ANS_sv_20250901_001_002",
    "businessCard": {
      "group1": {
        "email": "nishimura.misaki@example.com"
      },
      "group2": {
        "lastName": "西村",
        "firstName": "美咲"
      },
      "group3": {
        "companyName": "カスタマーリレーション株式会社",
        "department": "カスタマーリレーション",
        "position": "リレーションシップマネージャー"
      },
      "group4": {
        "postalCode": "530-0003",
        "address1": "大阪府大阪市北区堂島1-6-20",
        "address2": "堂島アバンザ 18F"
      },
      "group5": {
        "mobile": "060-8765-4321",
        "tel1": "06-4444-5555",
        "fax": "06-4444-5556"
      },
      "group6": {
        "url": "https://customer-relations.example.com"
      }
    }
  }
]